logafault/__init__.py
logafault/auth.py
logafault/exceptions.py
logafault/faults.py
logafault/models.py
logafault/py.typed
logafault-1.2.0.dist-info/LICENSE
logafault-1.2.0.dist-info/METADATA
logafault-1.2.0.dist-info/WHEEL
logafault-1.2.0.dist-info/top_level.txt
logafault-1.2.0.dist-info/RECORD
