Metadata-Version: 2.2
Name: logafault
Version: 1.2.0
Summary: An SDK for interacting with CityPower's APIs.
Home-page: https://github.com/cliftondhanee/logafault
Author: Clifton Dhanee
Author-email: clifton.dhanee@yahoo.com
License: MIT
Classifier: License :: OSI Approved :: MIT License
Classifier: Programming Language :: Python :: 3.9
Classifier: Operating System :: OS Independent
Requires-Python: >=3.9
License-File: LICENSE
Requires-Dist: requests
Requires-Dist: pydantic
Dynamic: author
Dynamic: author-email
Dynamic: classifier
Dynamic: description
Dynamic: description-content-type
Dynamic: home-page
Dynamic: license
Dynamic: requires-dist
Dynamic: requires-python
Dynamic: summary
